tamqp/__init__.py
tamqp/consumers/__init__.py
tamqp/consumers/job_consumer.py
tamqp/consumers/models/__init__.py
tamqp/consumers/models/communication_model.py
tamqp/consumers/models/communication_object.py
tamqp/consumers/models/test_model.py
tamqp/consumers/models/test_publish_model.py
tamqp/exceptions/__init__.py
tamqp/exceptions/channel_creation_exception.py
tamqp/exceptions/connection_refused_exception.py
tamqp/exceptions/enrolling_queue_exception.py
tamqp/exceptions/publish_message_exception.py
tamqp/exceptions/queue_declare_exception.py
tamqp/models/__init__.py
tamqp/models/amqp_init.py
tamqp/models/communication_wrapper.py
tamqp/models/rabbit_library.py
tamqp/models/retry_queue.py
tamqp/services/__init__.py
tamqp/services/amqp.py
tamqp/services/amqp_provider.py
tamqp/services/amqp_provider_config.py
tamqp/services/amqp_utils.py
tamqp/services/encoded_provider.py
tamqp/utils/__init__.py
tamqp/utils/string_decoder.py
tamqp-0.0.10.dist-info/METADATA
tamqp-0.0.10.dist-info/WHEEL
tamqp-0.0.10.dist-info/top_level.txt
tamqp-0.0.10.dist-info/RECORD
