Metadata-Version: 2.1
Name: tamqp
Version: 0.0.10
Summary: Adaptable Python library to interact with cloud RabbitMQ providers
Home-page: https://s-g@bitbucket.org/yployalty/tamqp
Author: Saurabh Gupta
Author-email: sgupta@taekus.com
License: GNU General Public License v3.0
Platform: UNKNOWN
Classifier: Development Status :: 3 - Alpha
Classifier: Programming Language :: Python :: 3
Classifier: Topic :: Software Development :: Libraries
Requires-Dist: pika (==1.3.2)
